vipurpca/PCA.py
vipurpca/__init__.py
vipurpca/helper_functions.py
vipurpca/load_data.py
vipurpca/data/__init__.py
vipurpca/data/estrogen_data.npz
vipurpca/data/studentsgrades_data.npz
vipurpca-0.0.2.dist-info/LICENSE
vipurpca-0.0.2.dist-info/METADATA
vipurpca-0.0.2.dist-info/WHEEL
vipurpca-0.0.2.dist-info/top_level.txt
vipurpca-0.0.2.dist-info/RECORD
