Metadata-Version: 2.1
Name: vipurpca
Version: 0.0.2
Summary: Visualizing and propagating uncertainty in PCA
Home-page: https://github.com/Integrative-Transcriptomics/VIPurPCA
Author: Susanne Zabel
Author-email: susizabel93@gmail.com
Project-URL: Bug Tracker, https://github.com/Integrative-Transcriptomics/VIPurPCA/issues
Classifier: Programming Language :: Python :: 3
Classifier: License :: OSI Approved :: MIT License
Classifier: Operating System :: OS Independent
Requires-Python: >=3.7
License-File: LICENSE
Requires-Dist: jax
Requires-Dist: jaxlib
Requires-Dist: matplotlib
Requires-Dist: numpy
Requires-Dist: psutil
Requires-Dist: scikit-learn
Requires-Dist: sklearn
